{
  "id": "fess206_exercises",
  "metadata": {
    "book": "NCERT: The Earth : Our Habitat - Textbook in Geography for Class VI",
    "bookId": "fess206",
    "curriculum": "CBSE",
    "grade": "6",
    "subject": "Geography",
    "timestamp": "2025-01-16T11:37:08.424Z",
    "chapter": "Our Country – India"
  },
  "exercises": [
    {
      "exerciseNumber": "1",
      "title": "Answer the following questions briefly.",
      "content": "(a) Name the major physical divisions of India.\n(b) India shares its land boundaries with seven countries. Name them.\n(c) Which two major rivers fall into the Arabian Sea?\n(d) Name the delta formed by the Ganga and the Brahmaputra.\n(e) How many States and Union Territories are there in India? Which states have a common capital?\n(f) Why do a large number of people live in the Northern plains?\n(g) Why is Lakshadweep known as a coral island?",
      "pages": [
        46
      ],
      "diagrams": []
    },
    {
      "exerciseNumber": "2",
      "title": "Tick the correct answers.",
      "content": "(a) The southernmost Himalayas are known as\n    (i) Shiwaliks (ii) Himadri (iii) Himachal\n(b) Sahyadris is also known as\n    (i) Aravali (ii) Western Ghats (iii) Himadri\n(c) The Palk Strait lies between the countries\n    (i) Sri Lanka and Maldives\n    (ii) India and Sri Lanka\n    (iii) India and Maldives\n(d) The Indian islands in the Arabian Sea are known as\n    (i) Andaman and Nicobar Islands\n    (ii) Lakshadweep Islands\n    (iii) Maldives\n(e) The oldest mountain range in India is the\n    (i) Aravali hills (ii) Western ghats (iii) Himalayas",
      "pages": [
        46,
        47
      ],
      "diagrams": []
    },
    {
      "exerciseNumber": "3",
      "title": "Fill in the blanks.",
      "content": "(a) India has an area of about ________________.\n(b) The Greater Himalayas are also known as_________________.\n(c) The river Narmada falls into the __________________ sea.\n(d) The latitude that runs almost halfway through India is ___________.",
      "pages": [
        47
      ],
      "diagrams": []
    },
    {
      "exerciseNumber": "4",
      "title": "Map skills",
      "content": "1. On an outline map of India, mark the following.\n   (a) Tropic of Cancer\n   (b) Standard Meridian of India\n   (c) State in which you live\n   (d) Andaman Islands and Lakshadweep Islands\n   (e) Western Ghats and Eastern Ghats",
      "pages": [
        47
      ],
      "diagrams": []
    }
  ]
}